{
  "resourceType" : "ValueSet",
  "id" : "944f3b64-13e5-4f41-bdf6-82035de5010b-1076",
  "url" : "http://hl7.org/fhir/comparison/ValueSet/944f3b64-13e5-4f41-bdf6-82035de5010b-1076",
  "name" : "UnionJDV_J194-TypeCrise-RORAndJDV_J194-TypeCrise-ROR",
  "title" : "Union of null And null",
  "status" : "active",
  "date" : "2024-08-22T10:39:14+00:00",
  "compose" : {
    "include" : [{
      "concept" : [{
        "code" : "01",
        "display" : "PMIE 1"
      },
      {
        "code" : "02",
        "display" : "Situation sanitaire Exceptionnelle (SSE) (Plan blanc)"
      }]
    }]
  }
}