{
  "date" : "Thu, 30 Jan, 2025 17:28:10 +0000",
  "doco" : "For each file: start is seconds after start activity occurred. Length = milliseconds activity took",
  "files" : [
    {
      "name" : "/fsh-generated/resources/ImplementationGuide-ans.fhir.fr.sdo.json",
      "size" : 11116,
      "processes" : [
        {
          "activity" : "load",
          "start" : 91,
          "length" : 8
        },
        {
          "activity" : "checkR4R4B",
          "start" : 92,
          "length" : 1
        },
        {
          "activity" : "generateNarratives",
          "start" : 92,
          "length" : 105
        },
        {
          "activity" : "validate",
          "start" : 95,
          "length" : 694
        },
        {
          "activity" : "generate1",
          "start" : 100,
          "length" : 53
        },
        {
          "activity" : "generate2",
          "start" : 103,
          "length" : 53
        },
        {
          "activity" : "generateValidationPack",
          "start" : 120,
          "length" : 5
        }
      ]
    },
    {
      "name" : "fsh-generated/resources/Bundle-exemple-bundle-resultat-recherche-decision-evaluation-elements.json",
      "size" : 2535,
      "processes" : [
        {
          "activity" : "loadResources",
          "start" : 91,
          "length" : 5
        },
        {
          "activity" : "load-configure",
          "start" : 91,
          "length" : 1
        },
        {
          "activity" : "load",
          "start" : 91,
          "length" : 1
        },
        {
          "activity" : "generateNarratives",
          "start" : 92,
          "length" : 10
        },
        {
          "activity" : "validate",
          "start" : 100,
          "length" : 15
        },
        {
          "activity" : "generate1",
          "start" : 100,
          "length" : 18
        },
        {
          "activity" : "generate2",
          "start" : 103,
          "length" : 13
        }
      ]
    },
    {
      "name" : "fsh-generated/resources/Bundle-exemple-bundle-resultat-recherche-decision-evaluation.json",
      "size" : 2724,
      "processes" : [
        {
          "activity" : "loadResources",
          "start" : 91,
          "length" : 4
        },
        {
          "activity" : "load",
          "start" : 91,
          "length" : 1
        },
        {
          "activity" : "generateNarratives",
          "start" : 92,
          "length" : 4
        },
        {
          "activity" : "validate",
          "start" : 100,
          "length" : 12
        },
        {
          "activity" : "generate1",
          "start" : 100,
          "length" : 19
        },
        {
          "activity" : "generate2",
          "start" : 103,
          "length" : 12
        }
      ]
    },
    {
      "name" : "fsh-generated/resources/Bundle-exemple-sdo-bundle-resultat-recherche-notifications-esms.json",
      "size" : 11061,
      "processes" : [
        {
          "activity" : "loadResources",
          "start" : 91,
          "length" : 5
        },
        {
          "activity" : "load",
          "start" : 91,
          "length" : 3
        },
        {
          "activity" : "checkR4R4B",
          "start" : 92,
          "length" : 1
        },
        {
          "activity" : "generateNarratives",
          "start" : 92,
          "length" : 7
        },
        {
          "activity" : "validate",
          "start" : 100,
          "length" : 85
        },
        {
          "activity" : "generate1",
          "start" : 100,
          "length" : 35
        },
        {
          "activity" : "generate2",
          "start" : 103,
          "length" : 19
        }
      ]
    },
    {
      "name" : "fsh-generated/resources/CapabilityStatement-ESMSConsommateur.json",
      "size" : 2507,
      "processes" : [
        {
          "activity" : "loadResources",
          "start" : 91,
          "length" : 4
        },
        {
          "activity" : "load",
          "start" : 91,
          "length" : 3
        },
        {
          "activity" : "generateNarratives",
          "start" : 92,
          "length" : 12
        },
        {
          "activity" : "validate",
          "start" : 95,
          "length" : 11
        },
        {
          "activity" : "generate1",
          "start" : 100,
          "length" : 27
        },
        {
          "activity" : "generate2",
          "start" : 103,
          "length" : 15
        },
        {
          "activity" : "generateValidationPack",
          "start" : 120,
          "length" : 1
        }
      ]
    },
    {
      "name" : "fsh-generated/resources/CapabilityStatement-ESMSProducteur.json",
      "size" : 1912,
      "processes" : [
        {
          "activity" : "loadResources",
          "start" : 91,
          "length" : 4
        },
        {
          "activity" : "load",
          "start" : 91,
          "length" : 2
        },
        {
          "activity" : "generateNarratives",
          "start" : 92,
          "length" : 10
        },
        {
          "activity" : "validate",
          "start" : 95,
          "length" : 6
        },
        {
          "activity" : "generate1",
          "start" : 100,
          "length" : 26
        },
        {
          "activity" : "generate2",
          "start" : 103,
          "length" : 14
        },
        {
          "activity" : "generateValidationPack",
          "start" : 120,
          "length" : 1
        }
      ]
    },
    {
      "name" : "fsh-generated/resources/CapabilityStatement-gestionnaire-sdo.json",
      "size" : 2756,
      "processes" : [
        {
          "activity" : "loadResources",
          "start" : 91,
          "length" : 4
        },
        {
          "activity" : "load",
          "start" : 91,
          "length" : 2
        },
        {
          "activity" : "generateNarratives",
          "start" : 92,
          "length" : 10
        },
        {
          "activity" : "validate",
          "start" : 95,
          "length" : 5
        },
        {
          "activity" : "generate1",
          "start" : 100,
          "length" : 20
        },
        {
          "activity" : "generate2",
          "start" : 103,
          "length" : 15
        },
        {
          "activity" : "generateValidationPack",
          "start" : 120,
          "length" : 1
        }
      ]
    },
    {
      "name" : "fsh-generated/resources/CodeSystem-input-task-sdo-codesystem.json",
      "size" : 4297,
      "processes" : [
        {
          "activity" : "loadResources",
          "start" : 91,
          "length" : 4
        },
        {
          "activity" : "load",
          "start" : 91,
          "length" : 5
        },
        {
          "activity" : "generateNarratives",
          "start" : 92,
          "length" : 7
        },
        {
          "activity" : "validate",
          "start" : 92,
          "length" : 404
        },
        {
          "activity" : "generate1",
          "start" : 100,
          "length" : 27
        },
        {
          "activity" : "generate2",
          "start" : 103,
          "length" : 1745
        },
        {
          "activity" : "generateValidationPack",
          "start" : 120,
          "length" : 1
        }
      ]
    },
    {
      "name" : "fsh-generated/resources/Consent-exemple-consent.json",
      "size" : 1058,
      "processes" : [
        {
          "activity" : "loadResources",
          "start" : 91,
          "length" : 4
        },
        {
          "activity" : "generateNarratives",
          "start" : 92,
          "length" : 131
        },
        {
          "activity" : "validate",
          "start" : 100,
          "length" : 14
        },
        {
          "activity" : "generate1",
          "start" : 100,
          "length" : 15
        },
        {
          "activity" : "generate2",
          "start" : 105,
          "length" : 12
        }
      ]
    },
    {
      "name" : "fsh-generated/resources/DocumentReference-exemple-esms-document-reference.json",
      "size" : 756,
      "processes" : [
        {
          "activity" : "loadResources",
          "start" : 91,
          "length" : 4
        },
        {
          "activity" : "validate",
          "start" : 100,
          "length" : 5
        },
        {
          "activity" : "generate1",
          "start" : 100,
          "length" : 11
        },
        {
          "activity" : "generate2",
          "start" : 105,
          "length" : 9
        }
      ]
    },
    {
      "name" : "fsh-generated/resources/DocumentReference-exemple-sdo-document-reference.json",
      "size" : 545,
      "processes" : [
        {
          "activity" : "loadResources",
          "start" : 91,
          "length" : 4
        },
        {
          "activity" : "generateNarratives",
          "start" : 92,
          "length" : 1
        },
        {
          "activity" : "validate",
          "start" : 100,
          "length" : 2
        },
        {
          "activity" : "generate1",
          "start" : 100,
          "length" : 10
        },
        {
          "activity" : "generate2",
          "start" : 105,
          "length" : 6
        }
      ]
    },
    {
      "name" : "fsh-generated/resources/StructureDefinition-esms-bundle-resultat-recherche-decision-evaluation.json",
      "size" : 1320,
      "processes" : [
        {
          "activity" : "loadResources",
          "start" : 91,
          "length" : 4
        },
        {
          "activity" : "load",
          "start" : 91,
          "length" : 3
        },
        {
          "activity" : "generateSnapshots",
          "start" : 91,
          "length" : 35
        },
        {
          "activity" : "generateNarratives",
          "start" : 92,
          "length" : 16
        },
        {
          "activity" : "validate",
          "start" : 92,
          "length" : 218
        },
        {
          "activity" : "scanForUsageStats",
          "start" : 100,
          "length" : 1
        },
        {
          "activity" : "generate1",
          "start" : 100,
          "length" : 114
        },
        {
          "activity" : "generate2",
          "start" : 105,
          "length" : 364
        },
        {
          "activity" : "generateExampleZip",
          "start" : 120,
          "length" : 1
        },
        {
          "activity" : "generateValidationPack",
          "start" : 120,
          "length" : 8
        }
      ]
    },
    {
      "name" : "fsh-generated/resources/StructureDefinition-esms-consent.json",
      "size" : 3458,
      "processes" : [
        {
          "activity" : "loadResources",
          "start" : 91,
          "length" : 5
        },
        {
          "activity" : "load",
          "start" : 91,
          "length" : 3
        },
        {
          "activity" : "generateSnapshots",
          "start" : 91,
          "length" : 29
        },
        {
          "activity" : "generateNarratives",
          "start" : 92,
          "length" : 27
        },
        {
          "activity" : "validate",
          "start" : 93,
          "length" : 436
        },
        {
          "activity" : "scanForUsageStats",
          "start" : 100,
          "length" : 1
        },
        {
          "activity" : "generate1",
          "start" : 100,
          "length" : 203
        },
        {
          "activity" : "generate2",
          "start" : 105,
          "length" : 636
        },
        {
          "activity" : "generateValidationPack",
          "start" : 120,
          "length" : 15
        },
        {
          "activity" : "scanExamplesForR5",
          "start" : 129,
          "length" : 1
        }
      ]
    },
    {
      "name" : "fsh-generated/resources/StructureDefinition-esms-document-reference.json",
      "size" : 2500,
      "processes" : [
        {
          "activity" : "loadResources",
          "start" : 91,
          "length" : 4
        },
        {
          "activity" : "load",
          "start" : 91,
          "length" : 3
        },
        {
          "activity" : "generateSnapshots",
          "start" : 91,
          "length" : 26
        },
        {
          "activity" : "generateNarratives",
          "start" : 92,
          "length" : 26
        },
        {
          "activity" : "validate",
          "start" : 93,
          "length" : 323
        },
        {
          "activity" : "scanForUsageStats",
          "start" : 100,
          "length" : 2
        },
        {
          "activity" : "generate1",
          "start" : 101,
          "length" : 175
        },
        {
          "activity" : "generate2",
          "start" : 106,
          "length" : 568
        },
        {
          "activity" : "generateValidationPack",
          "start" : 120,
          "length" : 14
        }
      ]
    },
    {
      "name" : "fsh-generated/resources/StructureDefinition-sdo-bundle-resultat-recherche-notification-esms.json",
      "size" : 1127,
      "processes" : [
        {
          "activity" : "loadResources",
          "start" : 91,
          "length" : 4
        },
        {
          "activity" : "load",
          "start" : 91,
          "length" : 2
        },
        {
          "activity" : "generateSnapshots",
          "start" : 91,
          "length" : 51
        },
        {
          "activity" : "generateNarratives",
          "start" : 92,
          "length" : 17
        },
        {
          "activity" : "validate",
          "start" : 93,
          "length" : 147
        },
        {
          "activity" : "generate1",
          "start" : 101,
          "length" : 99
        },
        {
          "activity" : "generate2",
          "start" : 106,
          "length" : 352
        },
        {
          "activity" : "generateValidationPack",
          "start" : 120,
          "length" : 11
        },
        {
          "activity" : "scanExamplesForR5",
          "start" : 129,
          "length" : 1
        }
      ]
    },
    {
      "name" : "fsh-generated/resources/StructureDefinition-sdo-document-reference.json",
      "size" : 3204,
      "processes" : [
        {
          "activity" : "loadResources",
          "start" : 91,
          "length" : 4
        },
        {
          "activity" : "load-configure",
          "start" : 91,
          "length" : 1
        },
        {
          "activity" : "load",
          "start" : 91,
          "length" : 2
        },
        {
          "activity" : "generateNarratives",
          "start" : 92,
          "length" : 27
        },
        {
          "activity" : "validate",
          "start" : 94,
          "length" : 273
        },
        {
          "activity" : "scanForUsageStats",
          "start" : 100,
          "length" : 2
        },
        {
          "activity" : "generate1",
          "start" : 101,
          "length" : 167
        },
        {
          "activity" : "generate2",
          "start" : 107,
          "length" : 456
        },
        {
          "activity" : "generateValidationPack",
          "start" : 120,
          "length" : 19
        }
      ]
    },
    {
      "name" : "fsh-generated/resources/StructureDefinition-sdo-task.json",
      "size" : 17930,
      "processes" : [
        {
          "activity" : "loadResources",
          "start" : 91,
          "length" : 6
        },
        {
          "activity" : "load",
          "start" : 91,
          "length" : 5
        },
        {
          "activity" : "generateSnapshots",
          "start" : 92,
          "length" : 27
        },
        {
          "activity" : "generateNarratives",
          "start" : 92,
          "length" : 54
        },
        {
          "activity" : "validate",
          "start" : 94,
          "length" : 661
        },
        {
          "activity" : "checkConformanceResources",
          "start" : 95,
          "length" : 1
        },
        {
          "activity" : "scanForUsageStats",
          "start" : 100,
          "length" : 2
        },
        {
          "activity" : "generate1",
          "start" : 101,
          "length" : 558
        },
        {
          "activity" : "generate2",
          "start" : 107,
          "length" : 1036
        },
        {
          "activity" : "generateValidationPack",
          "start" : 120,
          "length" : 44
        },
        {
          "activity" : "scanProfilesForR5",
          "start" : 129,
          "length" : 1
        },
        {
          "activity" : "scanExamplesForR5",
          "start" : 129,
          "length" : 1
        }
      ]
    },
    {
      "name" : "fsh-generated/resources/Task-exemple-sdo-task.json",
      "size" : 5986,
      "processes" : [
        {
          "activity" : "loadResources",
          "start" : 91,
          "length" : 5
        },
        {
          "activity" : "checkR4R4B",
          "start" : 92,
          "length" : 1
        },
        {
          "activity" : "generateNarratives",
          "start" : 92,
          "length" : 4
        },
        {
          "activity" : "validate",
          "start" : 100,
          "length" : 29
        },
        {
          "activity" : "generate1",
          "start" : 102,
          "length" : 17
        },
        {
          "activity" : "generate2",
          "start" : 108,
          "length" : 8
        }
      ]
    },
    {
      "name" : "fsh-generated/resources/ValueSet-type-document-reference-esms-valueset.json",
      "size" : 781,
      "processes" : [
        {
          "activity" : "loadResources",
          "start" : 91,
          "length" : 4
        },
        {
          "activity" : "load",
          "start" : 91,
          "length" : 2
        },
        {
          "activity" : "generateNarratives",
          "start" : 92,
          "length" : 32
        },
        {
          "activity" : "validate",
          "start" : 92,
          "length" : 11
        },
        {
          "activity" : "generate1",
          "start" : 102,
          "length" : 10
        },
        {
          "activity" : "generate2",
          "start" : 108,
          "length" : 3542
        },
        {
          "activity" : "generateValidationPack",
          "start" : 120,
          "length" : 1
        }
      ]
    }
  ]
}
